donordrivepython/__init__.py
donordrivepython/api/__init__.py
donordrivepython/api/activity.py
donordrivepython/api/badge.py
donordrivepython/api/comms.py
donordrivepython/api/donation.py
donordrivepython/api/donor.py
donordrivepython/api/participant.py
donordrivepython/api/team.py
donordrivepython/api/team_groups.py
donordrivepython/api/team_participant.py
donordrivepython/api/tests/__init__.py
donordrivepython/api/tests/test_badge.py
donordrivepython/api/tests/test_donation.py
donordrivepython/api/tests/test_donor.py
donordrivepython/api/tests/test_participant.py
donordrivepython/api/tests/test_team.py
donordrivepython/api/tests/test_team_participant.py
donordrivepython-1.6.0.dist-info/LICENSE
donordrivepython-1.6.0.dist-info/METADATA
donordrivepython-1.6.0.dist-info/WHEEL
donordrivepython-1.6.0.dist-info/RECORD
