Metadata-Version: 2.1
Name: donordrivepython
Version: 1.6.0
Summary: A utility to access the DonorDrive API
Home-page: https://github.com/djotaku/DonorDrivePython
License: GPL-3.0-or-later
Author: Eric Mesa
Author-email: ericsbinaryworld@gmail.com
Requires-Python: >=3.10,<4.0
Classifier: License :: OSI Approved :: GNU General Public License v3 or later (GPLv3+)
Classifier: Programming Language :: Python :: 3
Classifier: Programming Language :: Python :: 3.10
Classifier: Programming Language :: Python :: 3.11
Requires-Dist: requests (==2.28.1)
Requires-Dist: rich (>=12.4.4,<13.0.0)
Requires-Dist: xdgenvpy (>=2.3.5,<3.0.0)
Project-URL: Repository, https://github.com/djotaku/DonorDrivePython
